data_path.v
module data_path(
    input wire signed [63 : 0] istream_msg, //input stream message
    input wire [4 : 0] sparse_count,
    input clk,
    input rst,
    input state_done,
    input b_mux_sel,
    input a_mux_sel,
    input r_mux_sel,
    input add_mux_sel,
    input r_en,
    output b_lsb, //lsb : left significant bit
    output wire signed [31 : 0] ostream_msg,
    output reg signed [31 : 0] b_reg
); 

    wire signed [31 : 0] b_mux_out, b_rs_out; //rs : right shift
    wire signed [31 : 0] a_mux_out, a_ls_out; //ls : left shift
    wire signed [31 : 0] r_mux1_out, r_mux2_out, partial_sum;
    wire signed [31 : 0] a = istream_msg[63 : 32];
    wire signed [31 : 0] b = istream_msg[31 : 0];
    reg  signed [31 : 0] a_reg, r_reg;
    

    assign b_mux_out  = (b_mux_sel) ? b_rs_out : b;
    assign a_mux_out  = (a_mux_sel) ? a_ls_out : a;
    assign r_mux1_out = (r_mux_sel) ? r_mux2_out : 32'b0;
    assign r_mux2_out  = (add_mux_sel) ? partial_sum : r_reg;

    always @(posedge clk) begin
        b_reg <= b_mux_out;
        a_reg <= a_mux_out;
        if (r_en) begin
            r_reg <= r_mux1_out;
        end
    end

    assign b_rs_out = (!state_done) ? (b_reg >> sparse_count) : b_reg;
    assign a_ls_out = (!state_done) ? (a_reg << sparse_count) : a_reg;

    assign b_lsb = b_reg[0];
    assign ostream_msg = r_reg;
    assign partial_sum = a_reg + r_reg;

endmodule

sparse_counter.v
module sparse_counter(
    input rst,
    input wire [31 : 0] b_reg,
    output reg [4 : 0] sparse_count
);
    integer i;
    reg stop;

    always @(*) begin
        if(rst) begin
            sparse_count = 0;
            stop = 1;
        end
        else begin
            stop = 1;
            sparse_count = 5'd0;
            for(i = 0; i < 32; i = i + 1) begin
                if(stop) begin
                    if(b_reg[i] == 1'b1) begin
                        sparse_count = i;
                        stop = 0;
                    end
                end
            end
            if(sparse_count == 5'd0) sparse_count = 5'd1;
        end
    end

endmodule

control_unit.v
module control_unit(
    input clk,
    input rst,
    input b_lsb,
    input istream_val,
    input ostream_rdy,
    input wire [31 : 0] b_reg,
    output reg istream_rdy,
    output reg ostream_val,
    output reg b_mux_sel,
    output reg a_mux_sel,
    output reg r_mux_sel,
    output reg add_mux_sel,
    output reg r_en,
    output reg load_pulse,
    output reg state_done,
    output wire [4 : 0] sparse_count
);

    //s1,s2,s3 - FSM states
    //s1:idle, s2:calc, s3:done

    sparse_counter sc(
        .rst(rst),
        .b_reg(b_reg),
        .sparse_count(sparse_count)
    );

    parameter s0 = 2'd0, s1 = 2'd1, s2 = 2'd2, s3 = 2'd3;
    reg [1 : 0] state;
    reg [1 : 0] next_state;
    reg [5 : 0] counter;

    always @(posedge clk) begin
        if(rst) begin
            state <= s1;
            counter <= 6'b0;
        end

        else begin
            state <= next_state;
            if(state == s1 || state == s0) counter <= 6'b0;
            if(state == s2) counter <= counter + sparse_count;
        end
    end

    always @(*) begin
        b_mux_sel = 1'b1;
        a_mux_sel = 1'b1;
        r_mux_sel = 1'b0;
        state_done = 1'b0;
        next_state = state;
        add_mux_sel = 1'b0;
        r_en = 1'b0;
        istream_rdy = 1'b0;
        ostream_val = 1'b0;
        load_pulse = 1'b0;

        case(state)

        s0: begin
                b_mux_sel  = 1'b0;
                a_mux_sel  = 1'b0;
                r_mux_sel  = 1'b0;
                r_en       = 1'b1;
                load_pulse = 1'b1;
                next_state = s2;
            end

        s1: begin
                istream_rdy = 1'b1;
                if(istream_val) next_state = s0;
            end

        s2: begin
                b_mux_sel = 1'b1;
                a_mux_sel = 1'b1;
                r_mux_sel = 1'b1;

                if(counter >= 6'd32) next_state = s3;

                if(b_lsb) begin
                    add_mux_sel = 1'b1;
                    r_en = 1'b1;
                end

            end

        s3: begin
                state_done = 1'b1; 
                ostream_val = 1'b1;
                if(ostream_rdy) begin
                    next_state = s1;
                end
            end
        endcase
    end

endmodule

imul_main.v
module imul_main(
    input clk,
    input rst,

    input wire signed [63 : 0] istream_msg,
    input wire istream_val,
    output wire istream_rdy,

    output wire [31 : 0] ostream_msg,
    output wire ostream_val,
    input wire  ostream_rdy
);

    wire b_lsb, state_done, r_en, load_pulse;
    wire [4 : 0] sparse_count;
    wire a_mux_sel, b_mux_sel, r_mux_sel, add_mux_sel;
    wire signed [31 : 0] b_reg;
    
    reg sign_f;
    always @(posedge clk) begin
        if (rst) sign_f <= 1'b0;
        else if (load_pulse) sign_f <= istream_msg[63] ^ istream_msg[31];
    end

    wire sign_a = istream_msg[63];
    wire sign_b = istream_msg[31];
    wire [31 : 0] istream_a = (!sign_a) ? istream_msg[63 : 32] : ((~istream_msg[63 : 32]) + 32'd1);
    wire [31 : 0] istream_b = (!sign_b) ? istream_msg[31 : 0]  : ((~istream_msg[31 : 0])  + 32'd1);
    wire [63 : 0] istream_msg_mod = {istream_a, istream_b}; 

    wire [31 : 0] ostream_msg_mod;
    assign ostream_msg = (!sign_f) ? ostream_msg_mod : ((~ostream_msg_mod) + 32'd1);
    

    control_unit ctrl (
        .clk(clk),
        .rst(rst),
        .b_lsb(b_lsb),
        .istream_rdy(istream_rdy),
        .istream_val(istream_val),
        .ostream_rdy(ostream_rdy),
        .ostream_val(ostream_val),
        .a_mux_sel(a_mux_sel),
        .b_mux_sel(b_mux_sel),
        .r_mux_sel(r_mux_sel),
        .add_mux_sel(add_mux_sel),
        .r_en(r_en),
        .load_pulse(load_pulse),
        .state_done(state_done),
        .sparse_count(sparse_count),
        .b_reg(b_reg)
    );

    data_path data (
        .clk(clk),
        .rst(rst),
        .istream_msg(istream_msg_mod),
        .ostream_msg(ostream_msg_mod),
        .state_done(state_done),
        .a_mux_sel(a_mux_sel),
        .b_mux_sel(b_mux_sel),
        .r_mux_sel(r_mux_sel),
        .add_mux_sel(add_mux_sel),
        .r_en(r_en),
        .b_lsb(b_lsb),
        .sparse_count(sparse_count),
        .b_reg(b_reg)
    );

endmodule

sim/testbench.v
`timescale 1ns / 1ps

module tb;

    reg clk, rst;
    reg signed [63:0] istream_msg;
    reg istream_val;
    wire istream_rdy;
    wire signed [31:0] ostream_msg;
    wire ostream_val;
    reg ostream_rdy;

    imul_main dut (
        .clk(clk),
        .rst(rst),
        .istream_msg(istream_msg),
        .istream_val(istream_val),
        .istream_rdy(istream_rdy),
        .ostream_msg(ostream_msg),
        .ostream_val(ostream_val),
        .ostream_rdy(ostream_rdy)
    );

    always #5 clk = ~clk;

    task send_and_check;
        input signed [63:0] msg;
        input signed [31:0] expected;
        input [8*15-1:0] label;
        begin
            istream_msg = msg;
            istream_val = 1'b1;
            
            wait (istream_rdy == 1'b1);
            @(posedge clk);
            istream_val = 1'b0;

            wait (ostream_val == 1'b1);
            if (ostream_msg === expected)
                $display("PASS | %s | Got: %0d", label, ostream_msg);
            else
                $display("FAIL | %s | Got: %0d | Exp: %0d", label, ostream_msg, expected);

            ostream_rdy = 1'b1;
            @(posedge clk);
            ostream_rdy = 1'b0;
            #20;
        end
    endtask

    initial begin
        $dumpfile("dump.vcd");
        $dumpvars(0, tb);
        
        clk = 0; rst = 1;
        istream_msg = 0; istream_val = 0; ostream_rdy = 0;
        #20; rst = 0; #10;

        send_and_check({32'd3,   32'd10},       32'd30,          "3 * 10       ");
        send_and_check({-32'd5,  32'd6},        -32'd30,         "-5 * 6       ");
        send_and_check({32'd7,   -32'd4},       -32'd28,         "7 * -4       ");
        send_and_check({-32'd8,  -32'd9},       32'd72,          "-8 * -9      ");
        send_and_check({32'd0,   32'd15},       32'd0,           "0 * 15       ");
        send_and_check({32'd1,   -32'd99},      -32'd99,         "1 * -99      ");
        send_and_check({32'd255, 32'd255},      32'd65025,       "255 * 255    ");
        send_and_check({32'd3,   32'h80000000}, -32'd2147483648, "3 * 2^31     ");

        $finish;
    end

endmodule

dump.vcd
$date
	Mon Mar  2 21:21:00 2026
$end
$version
	Icarus Verilog
$end
$timescale
	1ps
$end
$scope module tb $end
$var wire 1 ! ostream_val $end
$var wire 32 " ostream_msg [31:0] $end
$var wire 1 # istream_rdy $end
$var reg 1 $ clk $end
$var reg 64 % istream_msg [63:0] $end
$var reg 1 & istream_val $end
$var reg 1 ' ostream_rdy $end
$var reg 1 ( rst $end
$scope module dut $end
$var wire 1 $ clk $end
$var wire 64 ) istream_msg [63:0] $end
$var wire 1 & istream_val $end
$var wire 1 ' ostream_rdy $end
$var wire 1 ( rst $end
$var wire 1 * state_done $end
$var wire 5 + sparse_count [4:0] $end
$var wire 1 , sign_b $end
$var wire 1 - sign_a $end
$var wire 1 . r_mux_sel $end
$var wire 1 / r_en $end
$var wire 1 ! ostream_val $end
$var wire 32 0 ostream_msg_mod [31:0] $end
$var wire 32 1 ostream_msg [31:0] $end
$var wire 1 2 load_pulse $end
$var wire 1 # istream_rdy $end
$var wire 64 3 istream_msg_mod [63:0] $end
$var wire 32 4 istream_b [31:0] $end
$var wire 32 5 istream_a [31:0] $end
$var wire 32 6 b_reg [31:0] $end
$var wire 1 7 b_mux_sel $end
$var wire 1 8 b_lsb $end
$var wire 1 9 add_mux_sel $end
$var wire 1 : a_mux_sel $end
$var reg 1 ; sign_f $end
$scope module ctrl $end
$var wire 1 $ clk $end
$var wire 1 & istream_val $end
$var wire 1 ' ostream_rdy $end
$var wire 1 ( rst $end
$var wire 5 < sparse_count [4:0] $end
$var wire 32 = b_reg [31:0] $end
$var wire 1 8 b_lsb $end
$var parameter 2 > s0 $end
$var parameter 2 ? s1 $end
$var parameter 2 @ s2 $end
$var parameter 2 A s3 $end
$var reg 1 : a_mux_sel $end
$var reg 1 9 add_mux_sel $end
$var reg 1 7 b_mux_sel $end
$var reg 6 B counter [5:0] $end
$var reg 1 # istream_rdy $end
$var reg 1 2 load_pulse $end
$var reg 2 C next_state [1:0] $end
$var reg 1 ! ostream_val $end
$var reg 1 / r_en $end
$var reg 1 . r_mux_sel $end
$var reg 2 D state [1:0] $end
$var reg 1 * state_done $end
$scope module sc $end
$var wire 1 ( rst $end
$var wire 32 E b_reg [31:0] $end
$var reg 5 F sparse_count [4:0] $end
$var reg 1 G stop $end
$var integer 32 H i [31:0] $end
$upscope $end
$upscope $end
$scope module data $end
$var wire 1 : a_mux_sel $end
$var wire 1 9 add_mux_sel $end
$var wire 1 7 b_mux_sel $end
$var wire 1 $ clk $end
$var wire 64 I istream_msg [63:0] $end
$var wire 32 J ostream_msg [31:0] $end
$var wire 1 / r_en $end
$var wire 1 . r_mux_sel $end
$var wire 1 ( rst $end
$var wire 5 K sparse_count [4:0] $end
$var wire 1 * state_done $end
$var wire 32 L r_mux2_out [31:0] $end
$var wire 32 M r_mux1_out [31:0] $end
$var wire 32 N partial_sum [31:0] $end
$var wire 32 O b_rs_out [31:0] $end
$var wire 32 P b_mux_out [31:0] $end
$var wire 1 8 b_lsb $end
$var wire 32 Q b [31:0] $end
$var wire 32 R a_mux_out [31:0] $end
$var wire 32 S a_ls_out [31:0] $end
$var wire 32 T a [31:0] $end
$var reg 32 U a_reg [31:0] $end
$var reg 32 V b_reg [31:0] $end
$var reg 32 W r_reg [31:0] $end
$upscope $end
$upscope $end
$scope task send_and_check $end
$var reg 32 X expected [31:0] $end
$var reg 120 Y label [119:0] $end
$var reg 64 Z msg [63:0] $end
$upscope $end
$upscope $end
$enddefinitions $end
$comment Show the parameter values. $end
$dumpall
b11 A
b10 @
b1 ?
b0 >
$end
#0
$dumpvars
bx Z
bx Y
bx X
bx W
bx V
bx U
b0 T
bx S
bx R
b0 Q
bx P
bx O
bx N
b0 M
bx L
b0 K
bx J
b0 I
bx H
xG
b0 F
bx E
bx D
bx C
bx B
bx =
b0 <
x;
1:
09
x8
17
bx 6
b0 5
b0 4
b0 3
02
bx 1
bx 0
0/
0.
0-
0,
b0 +
0*
b0 )
1(
0'
0&
b0 %
0$
0#
bx "
0!
$end
#5000
b0 R
b0 P
1#
b1 C
b0 L
b0 S
b0 O
08
b0 "
b0 1
b0 B
b1 D
b0 N
b0 0
b0 J
b0 W
b0 U
b0 6
b0 =
b0 E
b0 V
0;
1$
#10000
0$
#15000
1$
#20000
b1 +
b1 <
b1 F
b1 K
b100000 H
1G
0$
0(
#25000
1$
#30000
b11 T
b1010 Q
b11 5
b1100000000000000000000000000001010 3
b1100000000000000000000000000001010 I
b1010 4
b0 C
1#
0$
1&
b1100000000000000000000000000001010 %
b1100000000000000000000000000001010 )
b110011001000000010101000100000001100010011000000100000001000000010000000100000001000000010000000100000 Y
b11110 X
b1100000000000000000000000000001010 Z
#35000
b11 R
b1010 P
12
1/
0:
07
b0 D
0#
b10 C
0&
1$
#40000
0$
#45000
b110 R
b101 P
1.
02
0/
1:
17
b110 S
b101 O
0G
b100000 H
b1 +
b1 <
b1 F
b1 K
b10 D
b11 N
b11 U
b1010 6
b1010 =
b1010 E
b1010 V
1$
#50000
0$
#55000
b110 M
b110 L
b1100 R
b10 P
1/
19
b1100 S
b10 O
18
b100000 H
b1 +
b1 <
b1 F
b1 K
0G
1.
b110 N
b110 U
b101 6
b101 =
b101 E
b101 V
b1 B
1$
#60000
0$
#65000
b11000 R
b110 M
b1 P
0/
09
1.
b110 "
b110 1
b11000 S
b110 L
b1 O
08
b100000 H
b1 +
b1 <
b1 F
b1 K
0G
b10 B
b110 0
b110 J
b110 W
b10010 N
b1100 U
b10 6
b10 =
b10 E
b10 V
1$
#70000
0$
#75000
b11110 M
b11110 L
b110000 R
b0 P
1/
19
b110000 S
b0 O
18
b100000 H
b1 +
b1 <
b1 F
b1 K
0G
1.
b11110 N
b11000 U
b1 6
b1 =
b1 E
b1 V
b11 B
1$
#80000
0$
#85000
b1100000 R
b11110 M
0/
09
1.
b11110 "
b11110 1
b1100000 S
b11110 L
08
b100000 H
b1 +
b1 <
b1 F
b1 K
1G
b100 B
b11110 0
b11110 J
b11110 W
b1001110 N
b110000 U
b0 6
b0 =
b0 E
b0 V
1$
#90000
0$
#95000
b11000000 R
b11000000 S
1.
b1111110 N
b1100000 U
b101 B
1$
#100000
0$
#105000
b110000000 R
1.
b110000000 S
b110 B
b11011110 N
b11000000 U
1$
#110000
0$
#115000
b1100000000 R
b1100000000 S
1.
b110011110 N
b110000000 U
b111 B
1$
#120000
0$
#125000
b11000000000 R
1.
b11000000000 S
b1000 B
b1100011110 N
b1100000000 U
1$
#130000
0$
#135000
b110000000000 R
b110000000000 S
1.
b11000011110 N
b11000000000 U
b1001 B
1$
#140000
0$
#145000
b1100000000000 R
1.
b1100000000000 S
b1010 B
b110000011110 N
b110000000000 U
1$
#150000
0$
#155000
b11000000000000 R
b11000000000000 S
1.
b1100000011110 N
b1100000000000 U
b1011 B
1$
#160000
0$
#165000
b110000000000000 R
1.
b110000000000000 S
b1100 B
b11000000011110 N
b11000000000000 U
1$
#170000
0$
#175000
b1100000000000000 R
b1100000000000000 S
1.
b110000000011110 N
b110000000000000 U
b1101 B
1$
#180000
0$
#185000
b11000000000000000 R
1.
b11000000000000000 S
b1110 B
b1100000000011110 N
b1100000000000000 U
1$
#190000
0$
#195000
b110000000000000000 R
b110000000000000000 S
1.
b11000000000011110 N
b11000000000000000 U
b1111 B
1$
#200000
0$
#205000
b1100000000000000000 R
1.
b1100000000000000000 S
b10000 B
b110000000000011110 N
b110000000000000000 U
1$
#210000
0$
#215000
b11000000000000000000 R
b11000000000000000000 S
1.
b1100000000000011110 N
b1100000000000000000 U
b10001 B
1$
#220000
0$
#225000
b110000000000000000000 R
1.
b110000000000000000000 S
b10010 B
b11000000000000011110 N
b11000000000000000000 U
1$
#230000
0$
#235000
b1100000000000000000000 R
b1100000000000000000000 S
1.
b110000000000000011110 N
b110000000000000000000 U
b10011 B
1$
#240000
0$
#245000
b11000000000000000000000 R
1.
b11000000000000000000000 S
b10100 B
b1100000000000000011110 N
b1100000000000000000000 U
1$
#250000
0$
#255000
b110000000000000000000000 R
b110000000000000000000000 S
1.
b11000000000000000011110 N
b11000000000000000000000 U
b10101 B
1$
#260000
0$
#265000
b1100000000000000000000000 R
1.
b1100000000000000000000000 S
b10110 B
b110000000000000000011110 N
b110000000000000000000000 U
1$
#270000
0$
#275000
b11000000000000000000000000 R
b11000000000000000000000000 S
1.
b1100000000000000000011110 N
b1100000000000000000000000 U
b10111 B
1$
#280000
0$
#285000
b110000000000000000000000000 R
1.
b110000000000000000000000000 S
b11000 B
b11000000000000000000011110 N
b11000000000000000000000000 U
1$
#290000
0$
#295000
b1100000000000000000000000000 R
b1100000000000000000000000000 S
1.
b110000000000000000000011110 N
b110000000000000000000000000 U
b11001 B
1$
#300000
0$
#305000
b11000000000000000000000000000 R
1.
b11000000000000000000000000000 S
b11010 B
b1100000000000000000000011110 N
b1100000000000000000000000000 U
1$
#310000
0$
#315000
b110000000000000000000000000000 R
b110000000000000000000000000000 S
1.
b11000000000000000000000011110 N
b11000000000000000000000000000 U
b11011 B
1$
#320000
0$
#325000
b1100000000000000000000000000000 R
1.
b1100000000000000000000000000000 S
b11100 B
b110000000000000000000000011110 N
b110000000000000000000000000000 U
1$
#330000
0$
#335000
b11000000000000000000000000000000 R
b11000000000000000000000000000000 S
1.
b1100000000000000000000000011110 N
b1100000000000000000000000000000 U
b11101 B
1$
#340000
0$
#345000
b10000000000000000000000000000000 R
1.
b10000000000000000000000000000000 S
b11110 B
b11000000000000000000000000011110 N
b11000000000000000000000000000000 U
1$
#350000
0$
#355000
b0 R
b0 S
1.
b10000000000000000000000000011110 N
b10000000000000000000000000000000 U
b11111 B
1$
#360000
0$
#365000
b11 C
1.
b100000 B
b11110 N
b0 U
1$
#370000
0$
#375000
b1 C
1'
b0 M
1!
1*
0.
b100001 B
b11 D
1$
#380000
0$
#385000
1#
b1 D
0!
b1 C
0*
0'
1$
#390000
0$
#395000
1#
b0 B
1$
#400000
0$
#405000
b101 R
b110 P
12
1/
0:
07
b0 D
b101 T
b110 Q
b101 5
b10100000000000000000000000000000110 3
b10100000000000000000000000000000110 I
b110 4
b10 C
0#
1-
1$
0&
b1111111111111111111111111111101100000000000000000000000000000110 %
b1111111111111111111111111111101100000000000000000000000000000110 )
b101101001101010010000000101010001000000011011000100000001000000010000000100000001000000010000000100000 Y
b11111111111111111111111111100010 X
b1111111111111111111111111111101100000000000000000000000000000110 Z
#410000
0$
#415000
b1010 R
b11 P
b0 L
b0 "
b0 1
b1010 S
b11 O
0G
b100000 H
b1 +
b1 <
b1 F
b1 K
1.
02
0/
1:
17
1;
b0 0
b0 J
b0 W
b101 N
b101 U
b110 6
b110 =
b110 E
b110 V
b10 D
1$
#420000
0$
#425000
b1010 M
b1010 L
b10100 R
b1 P
1/
19
1.
b10100 S
b1 O
18
b100000 H
b1 +
b1 <
b1 F
b1 K
0G
b1 B
b1010 N
b1010 U
b11 6
b11 =
b11 E
b11 V
1$
#430000
0$
#435000
b11111111111111111111111111110110 "
b11111111111111111111111111110110 1
b101000 R
b0 P
b11110 M
b101000 S
b11110 L
b0 O
b100000 H
b1 +
b1 <
b1 F
b1 K
0G
1/
19
1.
b1010 0
b1010 J
b1010 W
b11110 N
b10100 U
b1 6
b1 =
b1 E
b1 V
b10 B
1$
#440000
0$
#445000
b11111111111111111111111111100010 "
b11111111111111111111111111100010 1
b1010000 R
b11110 M
0/
09
1.
b1010000 S
b11110 L
08
b100000 H
b1 +
b1 <
b1 F
b1 K
1G
b11 B
b11110 0
b11110 J
b11110 W
b1000110 N
b101000 U
b0 6
b0 =
b0 E
b0 V
1$
#450000
0$
#455000
b10100000 R
b10100000 S
1.
b1101110 N
b1010000 U
b100 B
1$
#460000
0$
#465000
b101000000 R
1.
b101000000 S
b101 B
b10111110 N
b10100000 U
1$
#470000
0$
#475000
b1010000000 R
b1010000000 S
1.
b101011110 N
b101000000 U
b110 B
1$
#480000
0$
#485000
b10100000000 R
1.
b10100000000 S
b111 B
b1010011110 N
b1010000000 U
1$
#490000
0$
#495000
b101000000000 R
b101000000000 S
1.
b10100011110 N
b10100000000 U
b1000 B
1$
#500000
0$
#505000
b1010000000000 R
1.
b1010000000000 S
b1001 B
b101000011110 N
b101000000000 U
1$
#510000
0$
#515000
b10100000000000 R
b10100000000000 S
1.
b1010000011110 N
b1010000000000 U
b1010 B
1$
#520000
0$
#525000
b101000000000000 R
1.
b101000000000000 S
b1011 B
b10100000011110 N
b10100000000000 U
1$
#530000
0$
#535000
b1010000000000000 R
b1010000000000000 S
1.
b101000000011110 N
b101000000000000 U
b1100 B
1$
#540000
0$
#545000
b10100000000000000 R
1.
b10100000000000000 S
b1101 B
b1010000000011110 N
b1010000000000000 U
1$
#550000
0$
#555000
b101000000000000000 R
b101000000000000000 S
1.
b10100000000011110 N
b10100000000000000 U
b1110 B
1$
#560000
0$
#565000
b1010000000000000000 R
1.
b1010000000000000000 S
b1111 B
b101000000000011110 N
b101000000000000000 U
1$
#570000
0$
#575000
b10100000000000000000 R
b10100000000000000000 S
1.
b1010000000000011110 N
b1010000000000000000 U
b10000 B
1$
#580000
0$
#585000
b101000000000000000000 R
1.
b101000000000000000000 S
b10001 B
b10100000000000011110 N
b10100000000000000000 U
1$
#590000
0$
#595000
b1010000000000000000000 R
b1010000000000000000000 S
1.
b101000000000000011110 N
b101000000000000000000 U
b10010 B
1$
#600000
0$
#605000
b10100000000000000000000 R
1.
b10100000000000000000000 S
b10011 B
b1010000000000000011110 N
b1010000000000000000000 U
1$
#610000
0$
#615000
b101000000000000000000000 R
b101000000000000000000000 S
1.
b10100000000000000011110 N
b10100000000000000000000 U
b10100 B
1$
#620000
0$
#625000
b1010000000000000000000000 R
1.
b1010000000000000000000000 S
b10101 B
b101000000000000000011110 N
b101000000000000000000000 U
1$
#630000
0$
#635000
b10100000000000000000000000 R
b10100000000000000000000000 S
1.
b1010000000000000000011110 N
b1010000000000000000000000 U
b10110 B
1$
#640000
0$
#645000
b101000000000000000000000000 R
1.
b101000000000000000000000000 S
b10111 B
b10100000000000000000011110 N
b10100000000000000000000000 U
1$
#650000
0$
#655000
b1010000000000000000000000000 R
b1010000000000000000000000000 S
1.
b101000000000000000000011110 N
b101000000000000000000000000 U
b11000 B
1$
#660000
0$
#665000
b10100000000000000000000000000 R
1.
b10100000000000000000000000000 S
b11001 B
b1010000000000000000000011110 N
b1010000000000000000000000000 U
1$
#670000
0$
#675000
b101000000000000000000000000000 R
b101000000000000000000000000000 S
1.
b10100000000000000000000011110 N
b10100000000000000000000000000 U
b11010 B
1$
#680000
0$
#685000
b1010000000000000000000000000000 R
1.
b1010000000000000000000000000000 S
b11011 B
b101000000000000000000000011110 N
b101000000000000000000000000000 U
1$
#690000
0$
#695000
b10100000000000000000000000000000 R
b10100000000000000000000000000000 S
1.
b1010000000000000000000000011110 N
b1010000000000000000000000000000 U
b11100 B
1$
#700000
0$
#705000
b1000000000000000000000000000000 R
1.
b1000000000000000000000000000000 S
b11101 B
b10100000000000000000000000011110 N
b10100000000000000000000000000000 U
1$
#710000
0$
#715000
b10000000000000000000000000000000 R
b10000000000000000000000000000000 S
1.
b1000000000000000000000000011110 N
b1000000000000000000000000000000 U
b11110 B
1$
#720000
0$
#725000
b0 R
1.
b0 S
b11111 B
b10000000000000000000000000011110 N
b10000000000000000000000000000000 U
1$
#730000
0$
#735000
b11 C
1.
b11110 N
b0 U
b100000 B
1$
#740000
0$
#745000
b1 C
1'
b0 M
1!
1*
0.
b100001 B
b11 D
1$
#750000
0$
#755000
1#
b1 D
0!
b1 C
0*
0'
1$
#760000
0$
#765000
1#
b0 B
1$
#770000
0$
#775000
b111 R
b100 P
12
1/
0:
07
b0 D
b111 T
b100 Q
b111 5
b11100000000000000000000000000000100 3
b11100000000000000000000000000000100 I
b100 4
b10 C
0#
0-
1,
1$
0&
b11111111111111111111111111111111100 %
b11111111111111111111111111111111100 )
b110111001000000010101000100000001011010011010000100000001000000010000000100000001000000010000000100000 Y
b11111111111111111111111111100100 X
b11111111111111111111111111111111100 Z
#780000
0$
#785000
b11100 R
b1 P
b0 "
b0 1
1.
02
0/
1:
17
b0 L
b11100 S
b1 O
0G
b100000 H
b10 +
b10 <
b10 F
b10 K
b10 D
b0 0
b0 J
b0 W
b111 N
b111 U
b100 6
b100 =
b100 E
b100 V
1$
#790000
0$
#795000
b11100 M
b11100 L
b111000 R
b0 P
1/
19
b111000 S
b0 O
18
b100000 H
b1 +
b1 <
b1 F
b1 K
0G
1.
b11100 N
b11100 U
b1 6
b1 =
b1 E
b1 V
b10 B
1$
#800000
0$
#805000
b11111111111111111111111111100100 "
b11111111111111111111111111100100 1
b1110000 R
b11100 M
0/
09
1.
b1110000 S
b11100 L
08
b100000 H
b1 +
b1 <
b1 F
b1 K
1G
b11 B
b11100 0
b11100 J
b11100 W
b1010100 N
b111000 U
b0 6
b0 =
b0 E
b0 V
1$
#810000
0$
#815000
b11100000 R
b11100000 S
1.
b10001100 N
b1110000 U
b100 B
1$
#820000
0$
#825000
b111000000 R
1.
b111000000 S
b101 B
b11111100 N
b11100000 U
1$
#830000
0$
#835000
b1110000000 R
b1110000000 S
1.
b111011100 N
b111000000 U
b110 B
1$
#840000
0$
#845000
b11100000000 R
1.
b11100000000 S
b111 B
b1110011100 N
b1110000000 U
1$
#850000
0$
#855000
b111000000000 R
b111000000000 S
1.
b11100011100 N
b11100000000 U
b1000 B
1$
#860000
0$
#865000
b1110000000000 R
1.
b1110000000000 S
b1001 B
b111000011100 N
b111000000000 U
1$
#870000
0$
#875000
b11100000000000 R
b11100000000000 S
1.
b1110000011100 N
b1110000000000 U
b1010 B
1$
#880000
0$
#885000
b111000000000000 R
1.
b111000000000000 S
b1011 B
b11100000011100 N
b11100000000000 U
1$
#890000
0$
#895000
b1110000000000000 R
b1110000000000000 S
1.
b111000000011100 N
b111000000000000 U
b1100 B
1$
#900000
0$
#905000
b11100000000000000 R
1.
b11100000000000000 S
b1101 B
b1110000000011100 N
b1110000000000000 U
1$
#910000
0$
#915000
b111000000000000000 R
b111000000000000000 S
1.
b11100000000011100 N
b11100000000000000 U
b1110 B
1$
#920000
0$
#925000
b1110000000000000000 R
1.
b1110000000000000000 S
b1111 B
b111000000000011100 N
b111000000000000000 U
1$
#930000
0$
#935000
b11100000000000000000 R
b11100000000000000000 S
1.
b1110000000000011100 N
b1110000000000000000 U
b10000 B
1$
#940000
0$
#945000
b111000000000000000000 R
1.
b111000000000000000000 S
b10001 B
b11100000000000011100 N
b11100000000000000000 U
1$
#950000
0$
#955000
b1110000000000000000000 R
b1110000000000000000000 S
1.
b111000000000000011100 N
b111000000000000000000 U
b10010 B
1$
#960000
0$
#965000
b11100000000000000000000 R
1.
b11100000000000000000000 S
b10011 B
b1110000000000000011100 N
b1110000000000000000000 U
1$
#970000
0$
#975000
b111000000000000000000000 R
b111000000000000000000000 S
1.
b11100000000000000011100 N
b11100000000000000000000 U
b10100 B
1$
#980000
0$
#985000
b1110000000000000000000000 R
1.
b1110000000000000000000000 S
b10101 B
b111000000000000000011100 N
b111000000000000000000000 U
1$
#990000
0$
#995000
b11100000000000000000000000 R
b11100000000000000000000000 S
1.
b1110000000000000000011100 N
b1110000000000000000000000 U
b10110 B
1$
#1000000
0$
#1005000
b111000000000000000000000000 R
1.
b111000000000000000000000000 S
b10111 B
b11100000000000000000011100 N
b11100000000000000000000000 U
1$
#1010000
0$
#1015000
b1110000000000000000000000000 R
b1110000000000000000000000000 S
1.
b111000000000000000000011100 N
b111000000000000000000000000 U
b11000 B
1$
#1020000
0$
#1025000
b11100000000000000000000000000 R
1.
b11100000000000000000000000000 S
b11001 B
b1110000000000000000000011100 N
b1110000000000000000000000000 U
1$
#1030000
0$
#1035000
b111000000000000000000000000000 R
b111000000000000000000000000000 S
1.
b11100000000000000000000011100 N
b11100000000000000000000000000 U
b11010 B
1$
#1040000
0$
#1045000
b1110000000000000000000000000000 R
1.
b1110000000000000000000000000000 S
b11011 B
b111000000000000000000000011100 N
b111000000000000000000000000000 U
1$
#1050000
0$
#1055000
b11100000000000000000000000000000 R
b11100000000000000000000000000000 S
1.
b1110000000000000000000000011100 N
b1110000000000000000000000000000 U
b11100 B
1$
#1060000
0$
#1065000
b11000000000000000000000000000000 R
1.
b11000000000000000000000000000000 S
b11101 B
b11100000000000000000000000011100 N
b11100000000000000000000000000000 U
1$
#1070000
0$
#1075000
b10000000000000000000000000000000 R
b10000000000000000000000000000000 S
1.
b11000000000000000000000000011100 N
b11000000000000000000000000000000 U
b11110 B
1$
#1080000
0$
#1085000
b0 R
1.
b0 S
b11111 B
b10000000000000000000000000011100 N
b10000000000000000000000000000000 U
1$
#1090000
0$
#1095000
b11 C
1.
b11100 N
b0 U
b100000 B
1$
#1100000
0$
#1105000
b1 C
1'
b0 M
1!
1*
0.
b100001 B
b11 D
1$
#1110000
0$
#1115000
1#
b1 D
0!
b1 C
0*
0'
1$
#1120000
0$
#1125000
1#
b0 B
1$
#1130000
0$
#1135000
b1000 R
b1001 P
12
1/
0:
07
b0 D
b1001 Q
b1000 T
b1001 4
b100000000000000000000000000000001001 3
b100000000000000000000000000000001001 I
b1000 5
b10 C
0#
1-
1$
0&
b1111111111111111111111111111100011111111111111111111111111110111 %
b1111111111111111111111111111100011111111111111111111111111110111 )
b101101001110000010000000101010001000000010110100111001001000000010000000100000001000000010000000100000 Y
b1001000 X
b1111111111111111111111111111100011111111111111111111111111110111 Z
#1140000
0$
#1145000
b1000 M
b10000 R
b100 P
19
1.
02
1/
1:
17
b1000 L
b10000 S
b100 O
18
0G
b100000 H
b1 +
b1 <
b1 F
b1 K
b0 "
b0 1
b10 D
b0 0
b0 J
b0 W
b1000 N
b1000 U
b1001 6
b1001 =
b1001 E
b1001 V
0;
1$
#1150000
0$
